easybase/HBase.thrift
easybase/__init__.py
easybase/_version.py
easybase/batch.py
easybase/connection.py
easybase/kerberos.py
easybase/pool.py
easybase/table.py
easybase/util.py
easybase-1.1.3.dist-info/LICENSE.rst
easybase-1.1.3.dist-info/METADATA
easybase-1.1.3.dist-info/WHEEL
easybase-1.1.3.dist-info/top_level.txt
easybase-1.1.3.dist-info/RECORD
