Metadata-Version: 2.1
Name: easybase
Version: 1.1.3
Summary: Python/Python3 library to interact with Apache HBase,support HBase 2.0, time-range scan and HBase thrift 2 procotol. 
Home-page: https://github.com/wgzhao/easybase
Author: wgzhao
Author-email: wgzhao@gmail.com
License: MIT
Keywords: HBase,easybase,thrift2
Platform: UNKNOWN
Classifier: Development Status :: 5 - Production/Stable
Classifier: Intended Audience :: Developers
Classifier: License :: OSI Approved :: MIT License
Classifier: Programming Language :: Python :: 2
Classifier: Programming Language :: Python :: 2.7
Classifier: Programming Language :: Python :: 3
Classifier: Programming Language :: Python :: 3.6
Classifier: Programming Language :: Python :: 3.7
Classifier: Programming Language :: Python :: 3.8
Classifier: Topic :: Database
Classifier: Topic :: Software Development :: Libraries :: Python Modules
License-File: LICENSE.rst
Requires-Dist: thriftpy2 (>=0.4.5)
Requires-Dist: six (>=1.15.0)
Requires-Dist: pure-sasl (>=0.6.2)
Requires-Dist: kerberos (>=1.3.0)
